{"datas":[{"type":false,"isEnd":true,"words":["H","HA","HAR","HARE","HAREM","HAREM<==","B","BR","BRU","BRUT","BRUTE","BRUTE<==","F","FA","FAR","FARC","FARCI","FARCI<==","O","OS","OSE","OSER","OSERA","OSERA<==","S","SU","SUC","SUCR","SUCRE","SUCRE<=="],"validateWords":["HAREM","BRUTE","FARCI","OSERA","SUCRE"],"ntry":5,"goodWord":"RAMPE","tab":[[["H","G"],["A","V"],["R","J"],["E","J"],["M","J"]],[["B","G"],["R","J"],["U","G"],["T","G"],["E","V"]],[["F","G"],["A","V"],["R","J"],["C","G"],["I","G"]],[["O","G"],["S","G"],["E","J"],["R","J"],["A","J"]],[["S","G"],["U","G"],["C","G"],["R","J"],["E","V"]]]},{"type":false,"isEnd":true,"words":["M","MY","MYT","MYTH","MYTHO","MYTHO<==","S","SE","SER","SERB","SERBE","SERBE<==","T","TE","TER","TERR","TERRE","TERRE<==","J","JE","JET","JETA","JETAI","JETAI<==","T","TA","TAC","TACO","TACOT","TACOT<=="],"validateWords":["MYTHO","SERBE","TERRE","JETAI","TACOT"],"ntry":5,"goodWord":"NAZES","tab":[[["M","G"],["Y","G"],["T","G"],["H","G"],["O","G"]],[["S","J"],["E","J"],["R","G"],["B","G"],["E","G"]],[["T","G"],["E","J"],["R","G"],["R","G"],["E","G"]],[["J","G"],["E","J"],["T","G"],["A","J"],["I","G"]],[["T","G"],["A","V"],["C","G"],["O","G"],["T","G"]]]},{"type":false,"isEnd":true,"words":["C","CO","COC","COCU","COCUE","COCUE<==","B","BA","BAI","BAIS","BAISE","BAISE<==","V","VI","VIL","VILL","VILLE","VILLE<==","L","LO","LOG","LOGE","LOGES","LOGES<==","M","MY","MYO","MYOP","MYOPE","MYOPE<=="],"validateWords":["COCUE","BAISE","VILLE","LOGES","MYOPE"],"ntry":5,"goodWord":"LEGOS","tab":[[["C","G"],["O","J"],["C","G"],["U","G"],["E","J"]],[["B","G"],["A","G"],["I","G"],["S","J"],["E","J"]],[["V","G"],["I","G"],["L","J"],["L","G"],["E","J"]],[["L","V"],["O","J"],["G","V"],["E","J"],["S","V"]],[["M","G"],["Y","G"],["O","J"],["P","G"],["E","J"]]]},{"type":false,"isEnd":true,"words":["P","PO","POS","POST","POSTE","POSTE<==","F","FI","FIA","FIAI","FIAIS","FIAIS<==","V","VE","VER","VERV","VERVE","VERVE<==","A","AI","AIL","AILL","AILLE","AILLE<==","C","CR","CRE","CREE","CREEE","CREEE<=="],"validateWords":["POSTE","FIAIS","VERVE","AILLE","CREEE"],"ntry":5,"goodWord":"CARNE","tab":[[["P","G"],["O","G"],["S","G"],["T","G"],["E","V"]],[["F","G"],["I","G"],["A","J"],["I","G"],["S","G"]],[["V","G"],["E","G"],["R","V"],["V","G"],["E","V"]],[["A","J"],["I","G"],["L","G"],["L","G"],["E","V"]],[["C","V"],["R","J"],["E","G"],["E","G"],["E","V"]]]},{"type":false,"isEnd":true,"words":["R","RA","RAM","RAMP","RAMPE","RAMPE<==","B","BA","BAV","BAVE","BAVES","BAVES<==","E","EN","ENT","ENTR","ENTRE","ENTRE<==","V","VA","VAS","VASE","VASES","VASES<==","F","FU","FUM","FUME","FUMET","FUMET<=="],"validateWords":["RAMPE","BAVES","ENTRE","VASES","FUMET"],"ntry":5,"goodWord":"TIRES","tab":[[["R","J"],["A","G"],["M","G"],["P","G"],["E","J"]],[["B","G"],["A","G"],["V","G"],["E","V"],["S","V"]],[["E","J"],["N","G"],["T","J"],["R","J"],["E","G"]],[["V","G"],["A","G"],["S","G"],["E","V"],["S","V"]],[["F","G"],["U","G"],["M","G"],["E","V"],["T","J"]]]},{"type":false,"isEnd":true,"words":["N","NU","NUR","NURS","NURSE","NURSE<==","E","EX","EXI","EXIG","EXIGU","EXIGU<==","C","CA","CAL","CALM","CALME","CALME<==","X","XE","XEN","XENO","XENON","XENON<==","E","ER","ERR","ERRE","ERRES","ERRES<=="],"validateWords":["NURSE","EXIGU","CALME","XENON","ERRES"],"ntry":5,"goodWord":"ELEVE","tab":[[["N","G"],["U","G"],["R","G"],["S","G"],["E","V"]],[["E","V"],["X","G"],["I","G"],["G","G"],["U","G"]],[["C","G"],["A","G"],["L","J"],["M","G"],["E","V"]],[["X","G"],["E","J"],["N","G"],["O","G"],["N","G"]],[["E","V"],["R","G"],["R","G"],["E","J"],["S","G"]]]},{"type":false,"isEnd":true,"words":["M","MI","MIM","MIME","MIMES","MIMES<==","N","NI","NIE","NIER","NIERA","NIERA<==","P","PA","PAL","PALE","PALET","PALET<==","F","FU","FUT","FUTE","FUTES","FUTES<==","C","CH","CHI","CHIE","CHIES","CHIES<=="],"validateWords":["MIMES","NIERA","PALET","FUTES","CHIES"],"ntry":5,"goodWord":"TASSE","tab":[[["M","G"],["I","G"],["M","G"],["E","J"],["S","J"]],[["N","G"],["I","G"],["E","J"],["R","G"],["A","J"]],[["P","G"],["A","V"],["L","G"],["E","J"],["T","J"]],[["F","G"],["U","G"],["T","J"],["E","J"],["S","J"]],[["C","G"],["H","G"],["I","G"],["E","J"],["S","J"]]]},{"type":false,"isEnd":true,"words":["E","EV","EVI","EVIT","EVITE","EVITE<==","F","FA","FAX","FAXE","FAXES","FAXES<==","T","TE","TET","TETU","TETUE","TETUE<==","J","JU","JUG","JUGE","JUGES","JUGES<==","S","SU","SUF","SUFF","SUFFI","SUFFI<=="],"validateWords":["EVITE","FAXES","TETUE","JUGES","SUFFI"],"ntry":5,"goodWord":"VENEZ","tab":[[["E","J"],["V","J"],["I","G"],["T","G"],["E","J"]],[["F","G"],["A","G"],["X","G"],["E","V"],["S","G"]],[["T","G"],["E","V"],["T","G"],["U","G"],["E","J"]],[["J","G"],["U","G"],["G","G"],["E","V"],["S","G"]],[["S","G"],["U","G"],["F","G"],["F","G"],["I","G"]]]},{"type":false,"isEnd":true,"words":["T","TI","TIA","TIAM","TIAMA","TIAMA<==","D","DE","DED","DEDI","DEDIA","DEDIA<==","S","SO","SON","SONG","SONGE","SONGE<==","B","BA","BAF","BAFF","BAFFE","BAFFE<==","A","AH","AHU","AHUR","AHURI","AHURI<=="],"validateWords":["TIAMA","DEDIA","SONGE","BAFFE","AHURI"],"ntry":5,"goodWord":"FIXER","tab":[[["T","G"],["I","V"],["A","G"],["M","G"],["A","G"]],[["D","G"],["E","J"],["D","G"],["I","J"],["A","G"]],[["S","G"],["O","G"],["N","G"],["G","G"],["E","J"]],[["B","G"],["A","G"],["F","J"],["F","G"],["E","J"]],[["A","G"],["H","G"],["U","G"],["R","J"],["I","J"]]]},{"type":false,"isEnd":true,"words":["V","VO","VOL","VOLE","VOLES","VOLES<==","N","NI","NIA","NIAI","NIAIT","NIAIT<==","C","CA","CAB","CABL","CABLE","CABLE<==","V","VE","VEL","VELU","VELUS","VELUS<==","E","EM","EME","EMEU","EMEUS","EMEUS<=="],"validateWords":["VOLES","NIAIT","CABLE","VELUS","EMEUS"],"ntry":5,"goodWord":"SALTO","tab":[[["V","G"],["O","J"],["L","V"],["E","G"],["S","J"]],[["N","G"],["I","G"],["A","J"],["I","G"],["T","J"]],[["C","G"],["A","V"],["B","G"],["L","J"],["E","G"]],[["V","G"],["E","G"],["L","V"],["U","G"],["S","J"]],[["E","G"],["M","G"],["E","G"],["U","G"],["S","J"]]]}]}