{"datas":[{"type":false,"isEnd":true,"words":["R","RE","REC","RECI","RECIF","RECIF<==","V","VE","VEN","VENE","VENEZ","VENEZ<==","M","MO","MON","MONT","MONTE","MONTE<==","R","RE","REN","REND","RENDU","RENDU<==","C","CO","CON","CONT","CONTE","CONTE<=="],"validateWords":["RECIF","VENEZ","MONTE","RENDU","CONTE"],"ntry":5,"goodWord":"NAZES","tab":[[["R","G"],["E","J"],["C","G"],["I","G"],["F","G"]],[["V","G"],["E","G"],["N","J"],["E","V"],["Z","J"]],[["M","G"],["O","G"],["N","J"],["T","G"],["E","J"]],[["R","G"],["E","J"],["N","J"],["D","G"],["U","G"]],[["C","G"],["O","G"],["N","J"],["T","G"],["E","J"]]]},{"type":false,"isEnd":true,"words":["C","CA","CAL","CALM","CALME","CALME<==","B","BE","BET","BETE","BETES","BETES<==","V","VA","VAL","VALE","VALEZ","VALEZ<==","R","RE","REM","REMI","REMIX","REMIX<==","A","AS","ASS","ASSE","ASSEZ","ASSEZ<=="],"validateWords":["CALME","BETES","VALEZ","REMIX","ASSEZ"],"ntry":5,"goodWord":"LEGOS","tab":[[["C","G"],["A","G"],["L","J"],["M","G"],["E","J"]],[["B","G"],["E","V"],["T","G"],["E","G"],["S","V"]],[["V","G"],["A","G"],["L","J"],["E","J"],["Z","G"]],[["R","G"],["E","V"],["M","G"],["I","G"],["X","G"]],[["A","G"],["S","J"],["S","G"],["E","J"],["Z","G"]]]},{"type":false,"isEnd":true,"words":["P","PL","PLU","PLUI","PLUIE","PLUIE<==","V","VO","VOU","VOUE","VOUER","VOUER<==","C","CO","COM","COMM","COMME","COMME<==","R","RE","REC","RECU","RECUE","RECUE<==","H","HY","HYP","HYPE","HYPER","HYPER<=="],"validateWords":["PLUIE","VOUER","COMME","RECUE","HYPER"],"ntry":5,"goodWord":"RAMPE","tab":[[["P","J"],["L","G"],["U","G"],["I","G"],["E","V"]],[["V","G"],["O","G"],["U","G"],["E","J"],["R","J"]],[["C","G"],["O","G"],["M","V"],["M","G"],["E","V"]],[["R","V"],["E","G"],["C","G"],["U","G"],["E","V"]],[["H","G"],["Y","G"],["P","J"],["E","J"],["R","J"]]]},{"type":false,"isEnd":true,"words":["S","SO","SOU","SOUL","SOULE","SOULE<==","B","BO","BON","BOND","BONDE","BONDE<==","J","JO","JOU","JOUT","JOUTE","JOUTE<==","D","DO","DOS","DOSE","DOSER","DOSER<==","N","NA","NAZ","NAZE","NAZES","NAZES<=="],"validateWords":["SOULE","BONDE","JOUTE","DOSER","NAZES"],"ntry":5,"goodWord":"TASSE","tab":[[["S","J"],["O","G"],["U","G"],["L","G"],["E","V"]],[["B","G"],["O","G"],["N","G"],["D","G"],["E","V"]],[["J","G"],["O","G"],["U","G"],["T","J"],["E","V"]],[["D","G"],["O","G"],["S","V"],["E","J"],["R","G"]],[["N","G"],["A","V"],["Z","G"],["E","J"],["S","J"]]]},{"type":false,"isEnd":true,"words":["L","LA","LAV","LAVE","LAVER","LAVER<==","C","CA","CAB","CABA","CABAN","CABAN<==","R","RI","RIC","RICH","RICHE","RICHE<==","S","SA","SAL","SALU","SALUE","SALUE<==","V","VI","VIE","VIEU","VIEUX","VIEUX<=="],"validateWords":["LAVER","CABAN","RICHE","SALUE","VIEUX"],"ntry":5,"goodWord":"SALTO","tab":[[["L","J"],["A","V"],["V","G"],["E","G"],["R","G"]],[["C","G"],["A","V"],["B","G"],["A","G"],["N","G"]],[["R","G"],["I","G"],["C","G"],["H","G"],["E","G"]],[["S","V"],["A","V"],["L","V"],["U","G"],["E","G"]],[["V","G"],["I","G"],["E","G"],["U","G"],["X","G"]]]},{"type":false,"isEnd":true,"words":["C","CH","CHO","CHOM","CHOME","CHOME<==","E","EN","ENT","ENTR","ENTRA","ENTRA<==","L","LA","LAC","LACH","LACHE","LACHE<==","B","BO","BOG","BOGI","BOGIE","BOGIE<==","N","NO","NOY","NOYE","NOYEZ","NOYEZ<=="],"validateWords":["CHOME","ENTRA","LACHE","BOGIE","NOYEZ"],"ntry":5,"goodWord":"ELEVE","tab":[[["C","G"],["H","G"],["O","G"],["M","G"],["E","V"]],[["E","V"],["N","G"],["T","G"],["R","G"],["A","G"]],[["L","J"],["A","G"],["C","G"],["H","G"],["E","V"]],[["B","G"],["O","G"],["G","G"],["I","G"],["E","V"]],[["N","G"],["O","G"],["Y","G"],["E","J"],["Z","G"]]]},{"type":false,"isEnd":true,"words":["S","SP","SPE","SPEE","SPEED","SPEED<==","J","JA","JAU","JAUN","JAUNE","JAUNE<==","C","CR","CRI","CRIE","CRIES","CRIES<==","B","BE","BEE","BEEN","BEENT","BEENT<==","R","RE","REC","RECU","RECUL","RECUL<=="],"validateWords":["SPEED","JAUNE","CRIES","BEENT","RECUL"],"ntry":5,"goodWord":"TIRES","tab":[[["S","J"],["P","G"],["E","G"],["E","V"],["D","G"]],[["J","G"],["A","G"],["U","G"],["N","G"],["E","J"]],[["C","G"],["R","J"],["I","J"],["E","V"],["S","V"]],[["B","G"],["E","J"],["E","G"],["N","G"],["T","J"]],[["R","J"],["E","J"],["C","G"],["U","G"],["L","G"]]]},{"type":false,"isEnd":true,"words":["A","AY","AYA","AYAN","AYANT","AYANT<==","B","BO","BOR","BORD","BORDE","BORDE<==","L","LU","LUT","LUTI","LUTIN","LUTIN<==","F","FA","FAU","FAUT","FAUTE","FAUTE<==","B","BO","BON","BONN","BONNE","BONNE<=="],"validateWords":["AYANT","BORDE","LUTIN","FAUTE","BONNE"],"ntry":5,"goodWord":"CARNE","tab":[[["A","J"],["Y","G"],["A","G"],["N","V"],["T","G"]],[["B","G"],["O","G"],["R","V"],["D","G"],["E","V"]],[["L","G"],["U","G"],["T","G"],["I","G"],["N","J"]],[["F","G"],["A","V"],["U","G"],["T","G"],["E","V"]],[["B","G"],["O","G"],["N","G"],["N","V"],["E","V"]]]},{"type":false,"isEnd":true,"words":["L","LI","LIR","LIRA","LIRAI","LIRAI<==","V","VE","VER","VERT","VERTE","VERTE<==","G","GA","GAR","GARE","GARES","GARES<==","C","CA","CAN","CANE","CANES","CANES<==","B","BU","BUL","BULL","BULLE","BULLE<=="],"validateWords":["LIRAI","VERTE","GARES","CANES","BULLE"],"ntry":5,"goodWord":"FIXER","tab":[[["L","G"],["I","V"],["R","J"],["A","G"],["I","G"]],[["V","G"],["E","J"],["R","J"],["T","G"],["E","G"]],[["G","G"],["A","G"],["R","J"],["E","V"],["S","G"]],[["C","G"],["A","G"],["N","G"],["E","V"],["S","G"]],[["B","G"],["U","G"],["L","G"],["L","G"],["E","J"]]]},{"type":false,"isEnd":true,"words":["D","DA","DAT","DATE","DATES","DATES<==","T","TI","TIS","TISE","TISER","TISER<==","N","NA","NAZ","NAZE","NAZES","NAZES<==","S","SO","SOC","SOCL","SOCLE","SOCLE<==","G","GA","GAG","GAGE","GAGER","GAGER<=="],"validateWords":["DATES","TISER","NAZES","SOCLE","GAGER"],"ntry":5,"goodWord":"VENEZ","tab":[[["D","G"],["A","G"],["T","G"],["E","V"],["S","G"]],[["T","G"],["I","G"],["S","G"],["E","V"],["R","G"]],[["N","J"],["A","G"],["Z","J"],["E","V"],["S","G"]],[["S","G"],["O","G"],["C","G"],["L","G"],["E","J"]],[["G","G"],["A","G"],["G","G"],["E","V"],["R","G"]]]}]}