{"datas":[{"type":false,"isEnd":true,"words":["C","CL","CLO","CLOW","CLOWN","CLOWN<==","V","VE","VEN","VENT","VENTE","VENTE<==","H","HA","HAT","HATE","HATER","HATER<==","F","FI","FIN","FINE","FINES","FINES<==","R","RA","RAS","RAST","RASTA","RASTA<=="],"validateWords":["CLOWN","VENTE","HATER","FINES","RASTA"],"ntry":5,"goodWord":"LEGOS","tab":[[["C","G"],["L","J"],["O","J"],["W","G"],["N","G"]],[["V","G"],["E","V"],["N","G"],["T","G"],["E","G"]],[["H","G"],["A","G"],["T","G"],["E","J"],["R","G"]],[["F","G"],["I","G"],["N","G"],["E","J"],["S","V"]],[["R","G"],["A","G"],["S","J"],["T","G"],["A","G"]]]},{"type":false,"isEnd":true,"words":["C","CO","COR","CORS","CORSE","CORSE<==","J","JU","JUN","JUNT","JUNTE","JUNTE<==","F","FI","FIF","FIFR","FIFRE","FIFRE<==","L","LY","LYC","LYCR","LYCRA","LYCRA<==","M","MA","MAR","MARR","MARRE","MARRE<=="],"validateWords":["CORSE","JUNTE","FIFRE","LYCRA","MARRE"],"ntry":5,"goodWord":"FIXER","tab":[[["C","G"],["O","G"],["R","J"],["S","G"],["E","J"]],[["J","G"],["U","G"],["N","G"],["T","G"],["E","J"]],[["F","V"],["I","V"],["F","G"],["R","J"],["E","J"]],[["L","G"],["Y","G"],["C","G"],["R","J"],["A","G"]],[["M","G"],["A","G"],["R","J"],["R","G"],["E","J"]]]},{"type":false,"isEnd":true,"words":["P","PL","PLA","PLAC","PLACE","PLACE<==","D","DE","DEB","DEBA","DEBAT","DEBAT<==","C","CH","CHI","CHIE","CHIEE","CHIEE<==","M","MO","MOR","MORU","MORUE","MORUE<==","M","MA","MAN","MANI","MANIP","MANIP<=="],"validateWords":["PLACE","DEBAT","CHIEE","MORUE","MANIP"],"ntry":5,"goodWord":"TIRES","tab":[[["P","G"],["L","G"],["A","G"],["C","G"],["E","J"]],[["D","G"],["E","J"],["B","G"],["A","G"],["T","J"]],[["C","G"],["H","G"],["I","J"],["E","V"],["E","G"]],[["M","G"],["O","G"],["R","V"],["U","G"],["E","J"]],[["M","G"],["A","G"],["N","G"],["I","J"],["P","G"]]]},{"type":false,"isEnd":true,"words":["T","TA","TAP","TAPI","TAPIE","TAPIE<==","B","BE","BEC","BECT","BECTE","BECTE<==","T","TA","TAC","TACH","TACHE","TACHE<==","P","PR","PRI","PRIE","PRIES","PRIES<==","M","MA","MAR","MARI","MARIE","MARIE<=="],"validateWords":["TAPIE","BECTE","TACHE","PRIES","MARIE"],"ntry":5,"goodWord":"CARNE","tab":[[["T","G"],["A","V"],["P","G"],["I","G"],["E","V"]],[["B","G"],["E","G"],["C","J"],["T","G"],["E","V"]],[["T","G"],["A","V"],["C","J"],["H","G"],["E","V"]],[["P","G"],["R","J"],["I","G"],["E","J"],["S","G"]],[["M","G"],["A","V"],["R","V"],["I","G"],["E","V"]]]},{"type":false,"isEnd":true,"words":["C","CE","CER","CERN","CERNE","CERNE<==","C","CI","CIT","CITE","CITES","CITES<==","J","JU","JUR","JURE","JUREZ","JUREZ<==","C","CH","CHU","CHUT","CHUTE","CHUTE<==","B","BA","BAR","BARB","BARBU","BARBU<=="],"validateWords":["CERNE","CITES","JUREZ","CHUTE","BARBU"],"ntry":5,"goodWord":"RAMPE","tab":[[["C","G"],["E","G"],["R","J"],["N","G"],["E","V"]],[["C","G"],["I","G"],["T","G"],["E","J"],["S","G"]],[["J","G"],["U","G"],["R","J"],["E","J"],["Z","G"]],[["C","G"],["H","G"],["U","G"],["T","G"],["E","V"]],[["B","G"],["A","V"],["R","J"],["B","G"],["U","G"]]]},{"type":false,"isEnd":true,"words":["G","GE","GEA","GEAN","GEANT","GEANT<==","P","PO","POC","POCH","POCHE","POCHE<==","X","XI","XIE","XIEM","XIEME","XIEME<==","V","VA","VAI","VAIN","VAINS","VAINS<==","E","EP","EPU","EPUR","EPURE","EPURE<=="],"validateWords":["GEANT","POCHE","XIEME","VAINS","EPURE"],"ntry":5,"goodWord":"ELEVE","tab":[[["G","G"],["E","J"],["A","G"],["N","G"],["T","G"]],[["P","G"],["O","G"],["C","G"],["H","G"],["E","V"]],[["X","G"],["I","G"],["E","V"],["M","G"],["E","V"]],[["V","J"],["A","G"],["I","G"],["N","G"],["S","G"]],[["E","V"],["P","G"],["U","G"],["R","G"],["E","V"]]]},{"type":false,"isEnd":true,"words":["G","GA","GAV","GAVE","GAVEE","GAVEE<==","F","FO","FON","FOND","FONDE","FONDE<==","A","AR","ARO","AROM","AROME","AROME<==","D","DI","DIS","DISC","DISCO","DISCO<==","A","AU","AUD","AUDI","AUDIO","AUDIO<=="],"validateWords":["GAVEE","FONDE","AROME","DISCO","AUDIO"],"ntry":5,"goodWord":"TASSE","tab":[[["G","G"],["A","V"],["V","G"],["E","G"],["E","V"]],[["F","G"],["O","G"],["N","G"],["D","G"],["E","V"]],[["A","J"],["R","G"],["O","G"],["M","G"],["E","V"]],[["D","G"],["I","G"],["S","V"],["C","G"],["O","G"]],[["A","J"],["U","G"],["D","G"],["I","G"],["O","G"]]]},{"type":false,"isEnd":true,"words":["E","EU","EUS","EUSS","EUSSE","EUSSE<==","D","DE","DEA","DEAL","DEALE","DEALE<==","B","BO","BOT","BOTT","BOTTE","BOTTE<==","R","RO","ROU","ROUL","ROULE","ROULE<==","P","PE","PET","PETE","PETER","PETER<=="],"validateWords":["EUSSE","DEALE","BOTTE","ROULE","PETER"],"ntry":5,"goodWord":"VENEZ","tab":[[["E","J"],["U","G"],["S","G"],["S","G"],["E","J"]],[["D","G"],["E","V"],["A","G"],["L","G"],["E","J"]],[["B","G"],["O","G"],["T","G"],["T","G"],["E","J"]],[["R","G"],["O","G"],["U","G"],["L","G"],["E","J"]],[["P","G"],["E","V"],["T","G"],["E","V"],["R","G"]]]},{"type":false,"isEnd":true,"words":["D","DE","DEC","DECU","DECUS","DECUS<==","C","CO","COT","COTE","COTES","COTES<==","F","FR","FRI","FRIR","FRIRE","FRIRE<==","O","ON","ONC","ONCL","ONCLE","ONCLE<==","P","PI","PIA","PIAN","PIANO","PIANO<=="],"validateWords":["DECUS","COTES","FRIRE","ONCLE","PIANO"],"ntry":5,"goodWord":"SALTO","tab":[[["D","G"],["E","G"],["C","G"],["U","G"],["S","J"]],[["C","G"],["O","J"],["T","J"],["E","G"],["S","J"]],[["F","G"],["R","G"],["I","G"],["R","G"],["E","G"]],[["O","J"],["N","G"],["C","G"],["L","J"],["E","G"]],[["P","G"],["I","G"],["A","J"],["N","G"],["O","V"]]]},{"type":false,"isEnd":true,"words":["A","AN","ANE","ANET","ANETH","ANETH<==","N","NA","NAS","NASA","NASAL","NASAL<==","O","OU","OUT","OUTR","OUTRE","OUTRE<==","F","FO","FOL","FOLI","FOLIE","FOLIE<==","L","LA","LAR","LARD","LARDS","LARDS<=="],"validateWords":["ANETH","NASAL","OUTRE","FOLIE","LARDS"],"ntry":5,"goodWord":"NAZES","tab":[[["A","J"],["N","J"],["E","J"],["T","G"],["H","G"]],[["N","V"],["A","V"],["S","J"],["A","G"],["L","G"]],[["O","G"],["U","G"],["T","G"],["R","G"],["E","J"]],[["F","G"],["O","G"],["L","G"],["I","G"],["E","J"]],[["L","G"],["A","V"],["R","G"],["D","G"],["S","V"]]]}]}