{"datas":[{"type":false,"isEnd":true,"words":["B","BA","BAS","BASE","BASEZ","BASEZ<==","F","FU","FUM","FUME","FUMEE","FUMEE<==","N","NU","NUQ","NUQU","NUQUE","NUQUE<==","S","SO","SOY","SOYE","SOYEZ","SOYEZ<==","A","AI","AIG","AIGR","AIGRI","AIGRI<=="],"validateWords":["BASEZ","FUMEE","NUQUE","SOYEZ","AIGRI"],"ntry":5,"goodWord":"ELEVE","tab":[[["B","G"],["A","G"],["S","G"],["E","J"],["Z","G"]],[["F","G"],["U","G"],["M","G"],["E","J"],["E","V"]],[["N","G"],["U","G"],["Q","G"],["U","G"],["E","V"]],[["S","G"],["O","G"],["Y","G"],["E","J"],["Z","G"]],[["A","G"],["I","G"],["G","G"],["R","G"],["I","G"]]]},{"type":false,"isEnd":true,"words":["N","NO","NOI","NOIR","NOIRE","NOIRE<==","P","PL","PLA","PLAN","PLANT","PLANT<==","B","BL","BLA","BLAN","BLANC","BLANC<==","L","LA","LAB","LABO","LABOS","LABOS<==","P","PH","PHO","PHOT","PHOTO","PHOTO<=="],"validateWords":["NOIRE","PLANT","BLANC","LABOS","PHOTO"],"ntry":5,"goodWord":"TIRES","tab":[[["N","G"],["O","G"],["I","J"],["R","J"],["E","J"]],[["P","G"],["L","G"],["A","G"],["N","G"],["T","J"]],[["B","G"],["L","G"],["A","G"],["N","G"],["C","G"]],[["L","G"],["A","G"],["B","G"],["O","G"],["S","V"]],[["P","G"],["H","G"],["O","G"],["T","J"],["O","G"]]]},{"type":false,"isEnd":true,"words":["F","FU","FUT","FUTE","FUTES","FUTES<==","B","BE","BEM","BEMO","BEMOL","BEMOL<==","D","DO","DON","DONG","DONGS","DONGS<==","L","LA","LAN","LANC","LANCE","LANCE<==","P","PI","PIN","PINO","PINOT","PINOT<=="],"validateWords":["FUTES","BEMOL","DONGS","LANCE","PINOT"],"ntry":5,"goodWord":"VENEZ","tab":[[["F","G"],["U","G"],["T","G"],["E","V"],["S","G"]],[["B","G"],["E","V"],["M","G"],["O","G"],["L","G"]],[["D","G"],["O","G"],["N","V"],["G","G"],["S","G"]],[["L","G"],["A","G"],["N","V"],["C","G"],["E","J"]],[["P","G"],["I","G"],["N","V"],["O","G"],["T","G"]]]},{"type":false,"isEnd":true,"words":["R","RA","RAT","RATE","RATER","RATER<==","B","BO","BOU","BOUG","BOUGE","BOUGE<==","C","CH","CHE","CHEI","CHEIK","CHEIK<==","A","AI","AIL","AILE","AILES","AILES<==","A","AL","ALL","ALLI","ALLIE","ALLIE<=="],"validateWords":["RATER","BOUGE","CHEIK","AILES","ALLIE"],"ntry":5,"goodWord":"CARNE","tab":[[["R","J"],["A","V"],["T","G"],["E","J"],["R","G"]],[["B","G"],["O","G"],["U","G"],["G","G"],["E","V"]],[["C","V"],["H","G"],["E","J"],["I","G"],["K","G"]],[["A","J"],["I","G"],["L","G"],["E","J"],["S","G"]],[["A","J"],["L","G"],["L","G"],["I","G"],["E","V"]]]},{"type":false,"isEnd":true,"words":["T","TA","TAI","TAIG","TAIGA","TAIGA<==","M","MI","MIL","MILE","MILES","MILES<==","T","TA","TAU","TAUP","TAUPE","TAUPE<==","B","BA","BAS","BASE","BASES","BASES<==","M","MO","MON","MONT","MONTE","MONTE<=="],"validateWords":["TAIGA","MILES","TAUPE","BASES","MONTE"],"ntry":5,"goodWord":"TASSE","tab":[[["T","V"],["A","V"],["I","G"],["G","G"],["A","G"]],[["M","G"],["I","G"],["L","G"],["E","J"],["S","J"]],[["T","V"],["A","V"],["U","G"],["P","G"],["E","V"]],[["B","G"],["A","V"],["S","V"],["E","J"],["S","J"]],[["M","G"],["O","G"],["N","G"],["T","J"],["E","V"]]]},{"type":false,"isEnd":true,"words":["P","PA","PAT","PATE","PATEE","PATEE<==","A","AE","AER","AERE","AERES","AERES<==","J","JU","JUG","JUGE","JUGEZ","JUGEZ<==","F","FL","FLA","FLAN","FLANE","FLANE<==","T","TI","TIR","TIRE","TIREE","TIREE<=="],"validateWords":["PATEE","AERES","JUGEZ","FLANE","TIREE"],"ntry":5,"goodWord":"SALTO","tab":[[["P","G"],["A","V"],["T","J"],["E","G"],["E","G"]],[["A","J"],["E","G"],["R","G"],["E","G"],["S","J"]],[["J","G"],["U","G"],["G","G"],["E","G"],["Z","G"]],[["F","G"],["L","J"],["A","J"],["N","G"],["E","G"]],[["T","J"],["I","G"],["R","G"],["E","G"],["E","G"]]]},{"type":false,"isEnd":true,"words":["S","SA","SAL","SALU","SALUT","SALUT<==","M","MO","MOR","MORD","MORDS","MORDS<==","B","BE","BEN","BENI","BENIS","BENIS<==","F","FR","FRE","FREM","FREMI","FREMI<==","I","IC","ICO","ICON","ICONE","ICONE<=="],"validateWords":["SALUT","MORDS","BENIS","FREMI","ICONE"],"ntry":5,"goodWord":"RAMPE","tab":[[["S","G"],["A","V"],["L","G"],["U","G"],["T","G"]],[["M","J"],["O","G"],["R","J"],["D","G"],["S","G"]],[["B","G"],["E","J"],["N","G"],["I","G"],["S","G"]],[["F","G"],["R","J"],["E","J"],["M","J"],["I","G"]],[["I","G"],["C","G"],["O","G"],["N","G"],["E","V"]]]},{"type":false,"isEnd":true,"words":["B","BI","BIL","BILE","BILEZ","BILEZ<==","V","VI","VIO","VIOL","VIOLE","VIOLE<==","T","TE","TER","TERR","TERRA","TERRA<==","C","CA","CAT","CATC","CATCH","CATCH<==","B","BO","BOB","BOBO","BOBOS","BOBOS<=="],"validateWords":["BILEZ","VIOLE","TERRA","CATCH","BOBOS"],"ntry":5,"goodWord":"FIXER","tab":[[["B","G"],["I","V"],["L","G"],["E","V"],["Z","G"]],[["V","G"],["I","V"],["O","G"],["L","G"],["E","J"]],[["T","G"],["E","J"],["R","J"],["R","G"],["A","G"]],[["C","G"],["A","G"],["T","G"],["C","G"],["H","G"]],[["B","G"],["O","G"],["B","G"],["O","G"],["S","G"]]]},{"type":false,"isEnd":true,"words":["R","RO","RON","RONG","RONGE","RONGE<==","S","SK","SKI","SKIE","SKIER","SKIER<==","G","GA","GAG","GAGE","GAGES","GAGES<==","H","HA","HAU","HAUT","HAUTS","HAUTS<==","P","PI","PIP","PIPE","PIPER","PIPER<=="],"validateWords":["RONGE","SKIER","GAGES","HAUTS","PIPER"],"ntry":5,"goodWord":"NAZES","tab":[[["R","G"],["O","G"],["N","J"],["G","G"],["E","J"]],[["S","J"],["K","G"],["I","G"],["E","V"],["R","G"]],[["G","G"],["A","V"],["G","G"],["E","V"],["S","V"]],[["H","G"],["A","V"],["U","G"],["T","G"],["S","V"]],[["P","G"],["I","G"],["P","G"],["E","V"],["R","G"]]]},{"type":false,"isEnd":true,"words":["P","PO","POS","POST","POSTA","POSTA<==","M","MO","MOI","MOIS","MOISI","MOISI<==","C","CH","CHE","CHER","CHERE","CHERE<==","B","BO","BOU","BOUG","BOUGE","BOUGE<==","J","JE","JER","JERE","JEREZ","JEREZ<=="],"validateWords":["POSTA","MOISI","CHERE","BOUGE","JEREZ"],"ntry":5,"goodWord":"LEGOS","tab":[[["P","G"],["O","J"],["S","J"],["T","G"],["A","G"]],[["M","G"],["O","J"],["I","G"],["S","J"],["I","G"]],[["C","G"],["H","G"],["E","J"],["R","G"],["E","G"]],[["B","G"],["O","J"],["U","G"],["G","J"],["E","J"]],[["J","G"],["E","V"],["R","G"],["E","G"],["Z","G"]]]}]}